tap_woocommerce/__init__.py
tap_woocommerce/schemas/orders.json
tap_woocommerce/schemas/reports.json
tap_woocommerce_v3-0.3.4.dist-info/LICENSE
tap_woocommerce_v3-0.3.4.dist-info/METADATA
tap_woocommerce_v3-0.3.4.dist-info/WHEEL
tap_woocommerce_v3-0.3.4.dist-info/entry_points.txt
tap_woocommerce_v3-0.3.4.dist-info/top_level.txt
tap_woocommerce_v3-0.3.4.dist-info/RECORD
