Metadata-Version: 2.1
Name: tap-woocommerce-v3
Version: 0.3.4
Summary: Singer.io tap for extracting data
Home-page: http://singer.io
Author: Stitch
Author-email: UNKNOWN
License: UNKNOWN
Platform: UNKNOWN
Classifier: Programming Language :: Python :: 3 :: Only
Requires-Dist: unidecode (==1.2.0)
Requires-Dist: attrs (==18.1.0)
Requires-Dist: backoff (==1.3.2)
Requires-Dist: python-dateutil (==2.7.3)
Requires-Dist: requests (==2.20.0)
Requires-Dist: pendulum
Requires-Dist: singer-python (==5.0.15)
